Metadata-Version: 1.0
Name: surya-distributions
Version: 0.1
Summary: Gaussian and Binomial distributions
Home-page: UNKNOWN
Author: Surya Sanchez
Author-email: hello@suryasanchez.com
License: UNKNOWN
Platform: UNKNOWN
